climahe/__init__.py
climahe/climatex.py
py_climate_health_toolbox-0.0.2.dist-info/LICENSE.py
py_climate_health_toolbox-0.0.2.dist-info/METADATA
py_climate_health_toolbox-0.0.2.dist-info/WHEEL
py_climate_health_toolbox-0.0.2.dist-info/top_level.txt
py_climate_health_toolbox-0.0.2.dist-info/RECORD
