Metadata-Version: 2.1
Name: py-climate-health-toolbox
Version: 0.0.2
Summary: Toolbox to study the impact of climate extremes in health
Home-page: https://github.com/climate-and-health-datasci-Unicamp/py-climate-health-toolbox
Author: Climate and Health Research Group - Unicamp
Author-email: paulad@unicamp.br
License: UNKNOWN
Platform: UNKNOWN
Classifier: Programming Language :: Python :: 3
Classifier: License :: OSI Approved :: GNU General Public License v3 (GPLv3)
Classifier: Operating System :: OS Independent
Classifier: Development Status :: 4 - Beta
Requires-Python: >=3.6
